sel_rdb/Relay710.rdb
sel_rdb/__init__.py
sel_rdb/convert_txt_to_rdb.py
sel_rdb/create_minimal_rdb.py
sel_rdb/create_minimal_rdb_openpyxl.py
sel_rdb/create_placeholder_rdb.py
sel_rdb/create_rdb_com.py
sel_rdb/create_rdb_template.py
sel_rdb/extract_logic_section.py
sel_rdb/extract_settings.py
sel_rdb/interval_utils.py
sel_rdb/list_rdb_streams.py
sel_rdb/logic_analyzer.py
sel_rdb/logic_changer.py
sel_rdb/logic_manipulator_functions.py
sel_rdb/rdb_analyzer.py
sel_rdb/sel_logic_count.py
sel_rdb/test_package.py
sel_rdb/utils.py
SEL_Rdb-1.0.0.dist-info/LICENSE
SEL_Rdb-1.0.0.dist-info/METADATA
SEL_Rdb-1.0.0.dist-info/WHEEL
SEL_Rdb-1.0.0.dist-info/entry_points.txt
SEL_Rdb-1.0.0.dist-info/top_level.txt
SEL_Rdb-1.0.0.dist-info/RECORD
