Metadata-Version: 2.1
Name: SEL_Rdb
Version: 1.0.0
Summary: A comprehensive toolkit for working with SEL (Schweitzer Engineering Laboratories) .rdb relay database files
Home-page: https://github.com/your-username/SEL_Rdb
Author: AOUF Nihed
Author-email: AOUF Nihed <aouf_nihed@esgee-oran.dz>
License: MIT
Project-URL: Homepage, https://github.com/AoufNihed/SEL_RDB
Project-URL: Bug Tracker, https://github.com/AoufNihed/SEL_RDB/issues
Classifier: Development Status :: 4 - Beta
Classifier: Intended Audience :: Developers
Classifier: Intended Audience :: Science/Research
Classifier: Topic :: Software Development :: Libraries :: Python Modules
Classifier: Topic :: Scientific/Engineering :: Interface Engine/Protocol Translator
Classifier: License :: OSI Approved :: MIT License
Classifier: Operating System :: OS Independent
Classifier: Programming Language :: Python :: 3
Classifier: Programming Language :: Python :: 3.6
Classifier: Programming Language :: Python :: 3.7
Classifier: Programming Language :: Python :: 3.8
Classifier: Programming Language :: Python :: 3.9
Classifier: Programming Language :: Python :: 3.10
Classifier: Programming Language :: Python :: 3.11
Requires-Python: >=3.6
License-File: LICENSE
Requires-Dist: olefile
Requires-Dist: openpyxl
